{"files":{"apps/backend-hono/dist/README.md":{"size":118,"mtime_nanos":1782056275407414800,"mode":420,"is_dir":false},"apps/backend-hono/dist/index.js.map":{"size":1145313,"mtime_nanos":1782056275671889900,"mode":420,"is_dir":false},"apps/backend-hono/.turbo/turbo-build.log":{"size":483,"mtime_nanos":1782056286315771900,"mode":420,"is_dir":false},"apps/backend-hono/dist":{"size":0,"mtime_nanos":0,"mode":0,"is_dir":true},"apps/backend-hono/dist/index.js":{"size":557486,"mtime_nanos":1782056275671360900,"mode":420,"is_dir":false}},"order":["apps/backend-hono/.turbo/turbo-build.log","apps/backend-hono/dist","apps/backend-hono/dist/README.md","apps/backend-hono/dist/index.js","apps/backend-hono/dist/index.js.map"]}